vdw_surfgen/__init__.py
vdw_surfgen/cli.py
vdw_surfgen-0.5.5.dist-info/METADATA
vdw_surfgen-0.5.5.dist-info/WHEEL
vdw_surfgen-0.5.5.dist-info/entry_points.txt
vdw_surfgen-0.5.5.dist-info/top_level.txt
vdw_surfgen-0.5.5.dist-info/RECORD
